{"0OswWW37kueoxIzS//HqJA==":"promo%20uten%20intro.00_00_37_12.still013-kopi-1920x800.png","he6lZ53WOhk2C1Q4ODUq0Q==":"back%20of%20billions-122x76.png","ZfGYtnyWkhl+RPp/WzRu3w==":"back%20of%20billions%20hvit%20bakgrunn-196x122.png","H0ZV58T418/T3IgxkRCZuw==":"back%20of%20billions%20svart-228x143.png","jQDqxfc/GFH85RgQiN/qeQ==":"back%20of%20billions%20svart-228x143.png","IWPItUeR8H1Qp7B1Pxk62g==":"back%20of%20billions%20svart-228x143.png","SZkFDdfcjdJURxM/fd90ZA==":"promo%20uten%20intro.00_00_42_21.still014-1920x800.png"}